argclass/__init__.py
argclass/__main__.py
argclass/actions.py
argclass/defaults.py
argclass/factory.py
argclass/parser.py
argclass/py.typed
argclass/secret.py
argclass/store.py
argclass/types.py
argclass/utils.py
argclass-1.5.2.dist-info/METADATA
argclass-1.5.2.dist-info/WHEEL
argclass-1.5.2.dist-info/licenses/COPYING
argclass-1.5.2.dist-info/RECORD
