Metadata-Version: 2.4
Name: argclass
Version: 1.5.2
Summary: Declarative CLI parser with type hints, config files, and environment variables - zero dependencies
Project-URL: Homepage, https://github.com/mosquito/argclass
Project-URL: Documentation, https://docs.argclass.com
Project-URL: Source, https://github.com/mosquito/argclass
Project-URL: Tracker, https://github.com/mosquito/argclass/issues
Author-email: Dmitry Orlov <me@mosquito.su>
License-Expression: Apache-2.0
License-File: COPYING
Keywords: argparse,argument-parser,cli,command-line,config,dataclass,declarative,environment-variables,type-hints
Classifier: Development Status :: 5 - Production/Stable
Classifier: Environment :: Console
Classifier: Intended Audience :: Developers
Classifier: Intended Audience :: System Administrators
Classifier: License :: OSI Approved :: Apache Software License
Classifier: Operating System :: MacOS :: MacOS X
Classifier: Operating System :: Microsoft :: Windows
Classifier: Operating System :: POSIX
Classifier: Operating System :: POSIX :: Linux
Classifier: Programming Language :: Python
Classifier: Programming Language :: Python :: 3
Classifier: Programming Language :: Python :: 3 :: Only
Classifier: Programming Language :: Python :: 3.10
Classifier: Programming Language :: Python :: 3.11
Classifier: Programming Language :: Python :: 3.12
Classifier: Programming Language :: Python :: 3.13
Classifier: Programming Language :: Python :: 3.14
Classifier: Typing :: Typed
Requires-Python: <4,>=3.10
